NERDA_Con/__init__.py
NERDA_Con/datasets.py
NERDA_Con/models.py
NERDA_Con/networks.py
NERDA_Con/performance.py
NERDA_Con/precooked.py
NERDA_Con/predictions.py
NERDA_Con/preprocessing.py
NERDA_Con/training.py
NERDA_Con/utils.py
NERDA_Con-0.0.dist-info/LICENSE
NERDA_Con-0.0.dist-info/METADATA
NERDA_Con-0.0.dist-info/WHEEL
NERDA_Con-0.0.dist-info/top_level.txt
NERDA_Con-0.0.dist-info/RECORD
