Metadata-Version: 2.1
Name: NERDA-Con
Version: 0.0
Summary: Extending NERDA Library for Continual Learning
Home-page: https://github.com/SupritiVijay/NERDA-Con
Author: Supriti Vijay, Aman Priyanshu
Author-email: supriti.vijay@gmail.com
License: UNKNOWN
Platform: UNKNOWN
Classifier: Programming Language :: Python :: 3
Classifier: License :: OSI Approved :: MIT License
Requires-Python: >=3.6
License-File: LICENSE
Requires-Dist: torch
Requires-Dist: transformers
Requires-Dist: sklearn
Requires-Dist: nltk
Requires-Dist: pandas
Requires-Dist: progressbar
Requires-Dist: pyconll
